sidepose/__init__.py
sidepose/anchor_base.py
sidepose/anchors.py
sidepose/constants.py
sidepose/controller.py
sidepose/enums.py
sidepose/mapping.py
sidepose/model.py
sidepose/model_hub.py
sidepose/overlay.py
sidepose/backends/mediapipe_backend.py
sidepose/qml/Pose/PoseSpace.qml
sidepose-0.0.1.data/data/sidepose.png
sidepose-0.0.1.dist-info/METADATA
sidepose-0.0.1.dist-info/WHEEL
sidepose-0.0.1.dist-info/top_level.txt
sidepose-0.0.1.dist-info/RECORD
