Metadata-Version: 2.4
Name: sidepose
Version: 0.0.1
Summary: Qt/QML pose estimation components
Author: Sidepose Contributors
License: MIT License
Project-URL: Homepage, https://gitlab.com/acemetrics-oss/sidepose
Project-URL: Repository, https://gitlab.com/acemetrics-oss/sidepose.git
Classifier: Development Status :: 4 - Beta
Classifier: Intended Audience :: Developers
Classifier: Intended Audience :: Science/Research
Classifier: Operating System :: OS Independent
Classifier: License :: OSI Approved :: MIT License
Classifier: Programming Language :: Python :: 3
Classifier: Programming Language :: Python :: 3 :: Only
Classifier: Programming Language :: Python :: 3.10
Classifier: Programming Language :: Python :: 3.11
Classifier: Programming Language :: Python :: 3.12
Classifier: Topic :: Scientific/Engineering :: Artificial Intelligence
Classifier: Topic :: Scientific/Engineering :: Image Processing
Classifier: Topic :: Multimedia :: Video
Classifier: Topic :: Multimedia :: Graphics
Requires-Python: >=3.10
Requires-Dist: PySide6>=6.5
Requires-Dist: numpy>=1.23
Provides-Extra: mediapipe
Requires-Dist: mediapipe>=0.10.7; extra == "mediapipe"
Provides-Extra: opencv
Requires-Dist: opencv-python>=4.7; extra == "opencv"
Provides-Extra: all
Requires-Dist: mediapipe>=0.10.7; extra == "all"
Requires-Dist: opencv-python>=4.7; extra == "all"
